pyhydllp/__init__.py
pyhydllp/base.py
pyhydllp/combo.py
pyhydllp/hyd.py
pyhydllp/hydllp.py
pyhydllp/sql.py
pyhydllp/util.py
pyhydllp/tests/__init__.py
pyhydllp/tests/test_base.py
pyhydllp/tests/test_combo.py
pyhydllp-1.1.5.dist-info/LICENSE.txt
pyhydllp-1.1.5.dist-info/METADATA
pyhydllp-1.1.5.dist-info/WHEEL
pyhydllp-1.1.5.dist-info/top_level.txt
pyhydllp-1.1.5.dist-info/RECORD
