Metadata-Version: 2.1
Name: pyhydllp
Version: 1.1.5
Summary: Class and functions to access Hydstra data and tools
Home-page: https://github.com/mullenkamp/pyhydllp
Author: Mike Kittridge
Author-email: mullenkamp1@gmail.com
License: Apache
Keywords: hydstra
Platform: UNKNOWN
Classifier: Development Status :: 3 - Alpha
Classifier: Intended Audience :: Developers
Classifier: Topic :: Software Development :: Build Tools
Classifier: License :: OSI Approved :: Apache Software License
Classifier: Programming Language :: Python :: 2
Classifier: Programming Language :: Python :: 2.7
Classifier: Programming Language :: Python :: 3
Classifier: Programming Language :: Python :: 3.4
Classifier: Programming Language :: Python :: 3.5
Classifier: Programming Language :: Python :: 3.6
Requires-Dist: pandas
